wxdc/WXBizDataCrypt.py
wxdc/__init__.py
wxdc-0.1.5.dist-info/METADATA
wxdc-0.1.5.dist-info/WHEEL
wxdc-0.1.5.dist-info/top_level.txt
wxdc-0.1.5.dist-info/RECORD
